README.rst
setup.cfg
setup.py
thriftgen/__init__.py
thriftgen/mainapp.py
thriftgen.egg-info/PKG-INFO
thriftgen.egg-info/SOURCES.txt
thriftgen.egg-info/dependency_links.txt
thriftgen.egg-info/entry_points.txt
thriftgen.egg-info/requires.txt
thriftgen.egg-info/top_level.txt
thriftgen/model/IAttributeHolder.py
thriftgen/model/ICommentable.py
thriftgen/model/IFileItem.py
thriftgen/model/ThriftyAttribute.py
thriftgen/model/ThriftyEnum.py
thriftgen/model/ThriftyException.py
thriftgen/model/ThriftyFile.py
thriftgen/model/ThriftyMethod.py
thriftgen/model/ThriftyService.py
thriftgen/model/ThriftyStruct.py
thriftgen/model/ThriftyType.py
thriftgen/model/ThrowsHolder.py
thriftgen/model/__init__.py
thriftgen/model/comment_parser.py
thriftgen/model/file_loader.py
thriftgen/parser/ThriftLexer.py
thriftgen/parser/ThriftListener.py
thriftgen/parser/ThriftParser.py
thriftgen/parser/__init__.py
thriftgen/parser/readme.txt
thriftgen/templates/__init__.py
thriftgen/templates/helpers_py3.py
thriftgen/templates/helpers_ts.py
thriftgen/test/__init__.py
thriftgen/test/model/__init__.py
thriftgen/test/model/test_file_loader.py