Metadata-Version: 1.0
Name: thriftgen
Version: 0.0.3
Summary: thriftgen
Home-page: UNKNOWN
Author: Bogdan Mustiata
Author-email: bogdan.mustiata@gmail.com
License: BSD
Platform: UNKNOWN
